{"type": "Feature", "id": 22656504, "geometry": {"type": "Point", "coordinates": [7.7422, 47.182201]}, "properties": {"woe:id": 22656504, "woe:parent_id": 20103180, "woe:name": "Flugplatz Langenthal", "woe:placetype": 14, "woe:placetype_name": "Airport", "woe:lang": "ENG", "iso:country": "CH", "meta:provider": ["geoplanet:7.3.1", "geoplanet:7.3.2", "geoplanet:7.4.0", "geoplanet:7.4.1", "geoplanet:7.5.1", "geoplanet:7.5.2", "geoplanet:7.6.0", "geoplanet:7.8.1", "geoplanet:7.9.0", "geoplanet:7.10.0", "geoplanet:8.0.0", "woeplanet:8.0.0"], "meta:indexed": "2020-08-20T21:03:05.061657", "woe:alias_GER_Q": ["Flugplatz Langenthal-Bleienbach"], "meta:updated": "2020-10-14T12:01:57.298342", "woe:alias_GER_V": ["Flugplatz Bleienbach"], "woe:hierarchy": {"continent": 24865675, "country": 23424957, "town": 0, "planet": 1, "county": 22656504, "suburb": 0, "state": 2347087, "region": 0, "localadmin": 12685044}, "woe:timezone_id": 28350924, "woe:hash": "u0ms2jm8nrf8", "woe:centroid": [7.7422, 47.182201], "geom:latitude": 47.182201, "geom:longitude": 7.7422, "geom:hash": "u0ms2jm8nrf8", "woe:latitude": 47.182201, "geom:centroid": [7.7422, 47.182201], "woe:longitude": 7.7422, "woe:repo": "woeplanet-airport-ch", "geom:area": 0.0, "woe:scale": 19}}