{"type": "Feature", "id": 56051732, "properties": {"woe:id": 56051732, "woe:parent_id": 784023, "woe:name": "Aerodromo San Vittore", "woe:placetype": 14, "woe:placetype_name": "Airport", "woe:lang": "ITA", "iso:country": "CH", "meta:provider": ["geoplanet:7.3.1", "geoplanet:7.3.2", "geoplanet:7.4.0", "geoplanet:7.4.1", "geoplanet:7.5.1", "geoplanet:7.5.2", "geoplanet:7.6.0", "geoplanet:7.8.1", "geoplanet:7.9.0", "geoplanet:7.10.0", "geoplanet:8.0.0", "woeplanet:8.0.0"], "meta:indexed": "2020-08-20T21:03:05.091551", "meta:updated": "2020-08-22T02:50:38.385702", "woe:hierarchy": {"continent": 24865675, "country": 23424957, "town": 0, "planet": 1, "county": 12593142, "suburb": 0, "state": 2347091, "region": 0, "localadmin": 12683842}, "woe:timezone_id": 28350924, "woe:hash": "u0nrnb681583", "woe:centroid": [9.08917, 46.231861], "geom:latitude": 46.231861, "geom:longitude": 9.08917, "geom:hash": "u0nrnb681583", "woe:latitude": 46.231861, "geom:centroid": [9.08917, 46.231861], "woe:longitude": 9.08917, "woe:repo": "woeplanet-airport-ch"}, "geometry": {"coordinates": [9.08917, 46.231861], "type": "Point"}}