{"type": "Feature", "id": 22656519, "properties": {"woe:id": 22656519, "woe:parent_id": 15001132, "woe:name": "Aerodrome de Bex", "woe:placetype": 14, "woe:placetype_name": "Airport", "woe:lang": "ENG", "iso:country": "CH", "meta:provider": ["geoplanet:7.3.1", "geoplanet:7.3.2", "geoplanet:7.4.0", "geoplanet:7.4.1", "geoplanet:7.5.1", "geoplanet:7.5.2", "geoplanet:7.6.0", "geoplanet:7.8.1", "geoplanet:7.9.0", "geoplanet:7.10.0", "geoplanet:8.0.0", "woeplanet:8.0.0"], "meta:indexed": "2020-08-20T21:03:05.071992", "meta:updated": "2020-08-22T02:50:38.374076", "woe:alias_FRE_V": ["A\u00e9rodrome de Bex"], "woe:alias_FRE_Q": ["A\u00e9rodrome de Bex"], "woe:hierarchy": {"continent": 24865675, "country": 23424957, "town": 0, "planet": 1, "county": 12593122, "suburb": 0, "state": 2347105, "region": 0, "localadmin": 12682960}, "woe:timezone_id": 28350924, "woe:hash": "u0hzph8he7u6", "woe:centroid": [6.98745, 46.255981], "geom:latitude": 46.255981, "geom:longitude": 6.98745, "geom:hash": "u0hzph8he7u6", "woe:latitude": 46.255981, "geom:centroid": [6.98745, 46.255981], "woe:longitude": 6.98745, "woe:repo": "woeplanet-airport-ch"}, "geometry": {"coordinates": [6.98745, 46.255981], "type": "Point"}}